MANIFEST.in
README.rst
setup.py
PySensors.egg-info/PKG-INFO
PySensors.egg-info/SOURCES.txt
PySensors.egg-info/dependency_links.txt
PySensors.egg-info/top_level.txt
doc/Makefile
doc/conf.py
doc/index.rst
doc/make.bat
sensors/__init__.py
sensors/cli.py
sensors/stdc.py