Metadata-Version: 2.1
Name: PySensors
Version: 0.0.4
Summary: Python bindings to libsensors (via ctypes)
Home-page: http://pypi.python.org/pypi/PySensors/
Author: Marc 'BlackJack' Rintsch
Author-email: marc@rintsch.de
License: LGPL v2.1
Keywords: sensors,hardware,monitoring
Platform: UNKNOWN
Classifier: Development Status :: 3 - Alpha
Classifier: Intended Audience :: Developers
Classifier: License :: OSI Approved
Classifier: License :: OSI Approved :: GNU Lesser General Public License v2 or later (LGPLv2+)
Classifier: Operating System :: POSIX :: Linux
Classifier: Programming Language :: Python
Classifier: Programming Language :: Python :: 3
Classifier: Programming Language :: Python :: 3.6
Classifier: Programming Language :: Python :: Implementation
Classifier: Programming Language :: Python :: Implementation :: CPython
Classifier: Topic :: System
Classifier: Topic :: System :: Hardware
Classifier: Topic :: System :: Monitoring
Requires-Python: >=3.6
